rclab/__init__.py
rclab/DataView/run.py
rclab/DataView/log_browser.cpython-310-x86_64-linux-gnu.so
rclab/Manual/view.pdf
rclab/Instruments/Instrument.cpython-310-x86_64-linux-gnu.so
rclab/Base/base_root.cpython-310-x86_64-linux-gnu.so
rclab/Base/servers.cpython-310-x86_64-linux-gnu.so
rclab/Utils/tracer.cpython-310-x86_64-linux-gnu.so
rclab/Utils/common.cpython-310-x86_64-linux-gnu.so
rclab/Utils/rwjson.cpython-310-x86_64-linux-gnu.so
rclab/Utils/rwdata.cpython-310-x86_64-linux-gnu.so
rclab/Utils/pltr.cpython-310-x86_64-linux-gnu.so
rclab/Utils/loadcsv.cpython-310-x86_64-linux-gnu.so
rclab/Utils/multiploter/adj.cpython-310-x86_64-linux-gnu.so
rclab/Utils/multiploter/ds.cpython-310-x86_64-linux-gnu.so
rclab/Utils/multiploter/mulpltr.cpython-310-x86_64-linux-gnu.so
rclab/Utils/multiploter/ploter.cpython-310-x86_64-linux-gnu.so
rclab/Utils/multiploter/conf.cpython-310-x86_64-linux-gnu.so
rclab/Utils/multiploter/que.cpython-310-x86_64-linux-gnu.so
rclab-1.0.1.dist-info/RECORD
rclab-1.0.1.dist-info/WHEEL
rclab-1.0.1.dist-info/METADATA
rclab-1.0.1.dist-info/top_level.txt
